skiplistcollections.py
skiplistcollections-0.0.6.dist-info/DESCRIPTION.rst
skiplistcollections-0.0.6.dist-info/METADATA
skiplistcollections-0.0.6.dist-info/pydist.json
skiplistcollections-0.0.6.dist-info/RECORD
skiplistcollections-0.0.6.dist-info/top_level.txt
skiplistcollections-0.0.6.dist-info/WHEEL
